MH410D/BaseSensor.py
MH410D/MH410D.py
MH410D/__init__.py
MH410D-1.0.0.dist-info/METADATA
MH410D-1.0.0.dist-info/WHEEL
MH410D-1.0.0.dist-info/top_level.txt
MH410D-1.0.0.dist-info/RECORD
