Metadata-Version: 2.1
Name: MH410D
Version: 1.0.0
Summary: MH410D CO2 UART/V out 0-10.00% VOL Sensor.
Home-page: https://github.com/NekoSensors/MH410D
Author: Artem-Darius Weber
Author-email: neko-sensors@k-lab.su
Classifier: Programming Language :: Python :: 3
Classifier: License :: OSI Approved :: MIT License
Classifier: Operating System :: OS Independent
Requires-Python: >=3.6
Requires-Dist: pyserial
